xmark/XMark.py
xmark/__init__.py
xmark-1.0.0.dist-info/METADATA
xmark-1.0.0.dist-info/WHEEL
xmark-1.0.0.dist-info/top_level.txt
xmark-1.0.0.dist-info/RECORD
